perceiver_jax/__init__.py
perceiver_jax/perceiver_jax.py
perceiver_jax-0.0.3.dist-info/LICENSE
perceiver_jax-0.0.3.dist-info/METADATA
perceiver_jax-0.0.3.dist-info/WHEEL
perceiver_jax-0.0.3.dist-info/top_level.txt
perceiver_jax-0.0.3.dist-info/RECORD
